{
  "main": {
    "id": "58b9c094620a95b8",
    "type": "split",
    "children": [
      {
        "id": "7d7322303e0be4c0",
        "type": "tabs",
        "children": [
          {
            "id": "6586e1d222d71189",
            "type": "leaf",
            "state": {
              "type": "markdown",
              "state": {
                "file": "README.md",
                "mode": "source",
                "source": false
              },
              "icon": "lucide-file",
              "title": "README"
            }
          }
        ]
      }
    ],
    "direction": "vertical"
  },
  "left": {
    "id": "35675a379fa4f862",
    "type": "split",
    "children": [
      {
        "id": "ec6ee5821cc3d61e",
        "type": "tabs",
        "children": [
          {
            "id": "ba71db30b0739f69",
            "type": "leaf",
            "state": {
              "type": "file-explorer",
              "state": {
                "sortOrder": "alphabetical",
                "autoReveal": false
              },
              "icon": "lucide-folder-closed",
              "title": "Explorador de archivos"
            }
          },
          {
            "id": "b2f1879e0b13872f",
            "type": "leaf",
            "state": {
              "type": "search",
              "state": {
                "query": "",
                "matchingCase": false,
                "explainSearch": false,
                "collapseAll": false,
                "extraContext": false,
                "sortOrder": "alphabetical"
              },
              "icon": "lucide-search",
              "title": "Buscar"
            }
          },
          {
            "id": "9359345c9f86dead",
            "type": "leaf",
            "state": {
              "type": "bookmarks",
              "state": {},
              "icon": "lucide-bookmark",
              "title": "Marcadores"
            }
          }
        ]
      }
    ],
    "direction": "horizontal",
    "width": 300
  },
  "right": {
    "id": "dcf1462ebaf8a4df",
    "type": "split",
    "children": [
      {
        "id": "87ec064e36a3df33",
        "type": "tabs",
        "children": [
          {
            "id": "94554a3f93917cc8",
            "type": "leaf",
            "state": {
              "type": "backlink",
              "state": {
                "file": "README.md",
                "collapseAll": false,
                "extraContext": false,
                "sortOrder": "alphabetical",
                "showSearch": false,
                "searchQuery": "",
                "backlinkCollapsed": false,
                "unlinkedCollapsed": true
              },
              "icon": "links-coming-in",
              "title": "Enlaces entrantes de README"
            }
          },
          {
            "id": "251d2f195e70d049",
            "type": "leaf",
            "state": {
              "type": "outgoing-link",
              "state": {
                "file": "README.md",
                "linksCollapsed": false,
                "unlinkedCollapsed": true
              },
              "icon": "links-going-out",
              "title": "Enlaces salientes de README"
            }
          },
          {
            "id": "646c43f78b7fd64b",
            "type": "leaf",
            "state": {
              "type": "tag",
              "state": {
                "sortOrder": "frequency",
                "useHierarchy": true,
                "showSearch": false,
                "searchQuery": ""
              },
              "icon": "lucide-tags",
              "title": "Etiquetas"
            }
          },
          {
            "id": "63da2c23df1cc84e",
            "type": "leaf",
            "state": {
              "type": "all-properties",
              "state": {
                "sortOrder": "frequency",
                "showSearch": false,
                "searchQuery": ""
              },
              "icon": "lucide-archive",
              "title": "Todas las propiedades"
            }
          },
          {
            "id": "b403b2a70ba84692",
            "type": "leaf",
            "state": {
              "type": "outline",
              "state": {
                "file": "README.md",
                "followCursor": false,
                "showSearch": false,
                "searchQuery": ""
              },
              "icon": "lucide-list",
              "title": "Esquema de README"
            }
          }
        ]
      }
    ],
    "direction": "horizontal",
    "width": 300,
    "collapsed": true
  },
  "left-ribbon": {
    "hiddenItems": {
      "switcher:Abrir selector rápido": false,
      "graph:Abrir vista gráfica": false,
      "canvas:Crear nuevo lienzo": false,
      "daily-notes:Abrir la nota de hoy": false,
      "templates:Insertar plantilla": false,
      "command-palette:Abrir paleta de comandos": false,
      "bases:Crear nueva base": false,
      "obsidian-git:Open Git source control": false
    }
  },
  "active": "6586e1d222d71189",
  "lastOpenFiles": [
    "Sin título.canvas",
    "README.md",
    "Projects",
    "Concepts",
    "University/Portuguese",
    "University/Image Processing",
    "University/Compiler Theory",
    "University/Artificial Intelligence",
    "University/Networks and Protocols",
    "University/Web Development",
    "University"
  ]
}